{
  "venueName": "SHEPPARTON",
  "raceNumber": 2,
  "form": {
    "data": {
      "raceNumber": 2,
      "spectrumId": "SHEPPARTN0",
      "raceName": "SHEPPARTON NEWS",
      "raceDistance": 390,
      "trackDirection": "anticlockwise",
      "meeting": {
        "meetingName": "SHEPPARTON",
        "venueMnemonic": "SHE",
        "meetingDate": "2026-04-16",
        "location": "VIC",
        "raceType": "G",
        "weatherCondition": "FINE",
        "trackCondition": "GOOD",
        "sellCode": {
          "meetingCode": "E",
          "scheduledType": "G"
        }
      },
      "skyRacing": {
        "audio": "https://mediatabs.skyracing.com.au/Audio_Replay/2026/04/20260416SHEG02.mp3",
        "video": "https://mediatabs.skyracing.com.au/Race_Replay/2026/04/20260416SHEG02_V.mp4"
      },
      "hasParimutuel": true,
      "hasFixedOdds": false,
      "broadcastChannel": null,
      "broadcastChannels": [],
      "hasForm": true,
      "hasEarlySpeedRatings": true,
      "allIn": false,
      "cashOutEligibility": "Disabled",
      "allowBundle": false,
      "willHaveFixedOdds": true,
      "fixedOddsOnlineBetting": true,
      "raceStartTime": "2026-04-16T00:59:00.000Z",
      "raceClassConditions": "Tier 3 - Maiden",
      "apprenticesCanClaim": false,
      "prizeMoney": "$1530.00",
      "raceStatus": "Paying",
      "substitute": 2,
      "results": [
        [
          4
        ],
        [
          1
        ],
        [
          6
        ],
        [
          2
        ]
      ],
      "pools": [
        {
          "wageringProduct": "Win",
          "legNumber": 1,
          "poolStatusCode": "Closed",
          "cashOutEligibility": "Disabled",
          "legs": [
            {
              "legNumber": 1,
              "raceNumber": 2,
              "venueMnemonic": "SHE",
              "raceType": "G",
              "startTime": "2026-04-16T00:59:00.000Z"
            }
          ],
          "poolHistory": [
            {
              "poolTotal": 928.5,
              "poolTotalTime": "2026-04-16T01:00:55.000Z",
              "specialDisplayIndicator": false
            },
            {
              "poolTotal": 928.5,
              "poolTotalTime": "2026-04-16T00:59:48.000Z",
              "specialDisplayIndicator": false
            },
            {
              "poolTotal": 928.5,
              "poolTotalTime": "2026-04-16T00:59:48.000Z",
              "specialDisplayIndicator": false
            },
            {
              "poolTotal": 928.5,
              "poolTotalTime": "2026-04-16T00:59:22.000Z",
              "specialDisplayIndicator": false
            },
            {
              "poolTotal": 15,
              "poolTotalTime": "2026-04-16T00:43:36.000Z",
              "specialDisplayIndicator": true
            }
          ],
          "poolTotal": 928.5,
          "jackpot": 0,
          "cominglingHost": "NSW",
          "cominglingHostName": "NSW TAB",
          "cominglingGuests": true,
          "substitute": "NR"
        },
        {
          "wageringProduct": "Place",
          "legNumber": 1,
          "poolStatusCode": "Closed",
          "cashOutEligibility": "Disabled",
          "legs": [
            {
              "legNumber": 1,
              "raceNumber": 2,
              "venueMnemonic": "SHE",
              "raceType": "G",
              "startTime": "2026-04-16T00:59:00.000Z"
            }
          ],
          "poolTotal": 70.05,
          "jackpot": 0,
          "cominglingHost": "NSW",
          "cominglingHostName": "NSW TAB",
          "cominglingGuests": true,
          "substitute": "NR"
        },
        {
          "wageringProduct": "Quinella",
          "legNumber": 1,
          "poolStatusCode": "Closed",
          "cashOutEligibility": "Disabled",
          "legs": [
            {
              "legNumber": 1,
              "raceNumber": 2,
              "venueMnemonic": "SHE",
              "raceType": "G",
              "startTime": "2026-04-16T00:59:00.000Z"
            }
          ],
          "_links": {
            "approximates": "https://api.beta.tab.com.au/v1/tab-info-service/racing/dates/2026-04-16/meetings/G/SHE/races/2/pools/Quinella/approximates?jurisdiction=NSW"
          },
          "poolTotal": 373.38,
          "jackpot": 0,
          "cominglingHost": "NSW",
          "cominglingHostName": "NSW TAB",
          "cominglingGuests": true,
          "substitute": "NR"
        },
        {
          "wageringProduct": "Exacta",
          "legNumber": 1,
          "poolStatusCode": "Closed",
          "cashOutEligibility": "Disabled",
          "legs": [
            {
              "legNumber": 1,
              "raceNumber": 2,
              "venueMnemonic": "SHE",
              "raceType": "G",
              "startTime": "2026-04-16T00:59:00.000Z"
            }
          ],
          "_links": {
            "approximates": "https://api.beta.tab.com.au/v1/tab-info-service/racing/dates/2026-04-16/meetings/G/SHE/races/2/pools/Exacta/approximates?jurisdiction=NSW"
          },
          "poolTotal": 201.67,
          "jackpot": 0,
          "cominglingHost": "NSW",
          "cominglingHostName": "NSW TAB",
          "cominglingGuests": true,
          "substitute": "NR"
        },
        {
          "wageringProduct": "Duet",
          "legNumber": 1,
          "poolStatusCode": "Closed",
          "cashOutEligibility": "Disabled",
          "legs": [
            {
              "legNumber": 1,
              "raceNumber": 2,
              "venueMnemonic": "SHE",
              "raceType": "G",
              "startTime": "2026-04-16T00:59:00.000Z"
            }
          ],
          "_links": {
            "approximates": "https://api.beta.tab.com.au/v1/tab-info-service/racing/dates/2026-04-16/meetings/G/SHE/races/2/pools/Duet/approximates?jurisdiction=NSW"
          },
          "poolTotal": 0,
          "jackpot": 0,
          "cominglingHost": "NSW",
          "cominglingHostName": "NSW TAB",
          "cominglingGuests": true,
          "substitute": "NR"
        },
        {
          "wageringProduct": "Trifecta",
          "legNumber": 1,
          "poolStatusCode": "Closed",
          "cashOutEligibility": "Disabled",
          "legs": [
            {
              "legNumber": 1,
              "raceNumber": 2,
              "venueMnemonic": "SHE",
              "raceType": "G",
              "startTime": "2026-04-16T00:59:00.000Z"
            }
          ],
          "poolTotal": 488.65,
          "jackpot": 0,
          "cominglingHost": "NSW",
          "cominglingHostName": "NSW TAB",
          "cominglingGuests": true,
          "substitute": "NR"
        },
        {
          "wageringProduct": "FirstFour",
          "legNumber": 1,
          "poolStatusCode": "Closed",
          "cashOutEligibility": "Disabled",
          "legs": [
            {
              "legNumber": 1,
              "raceNumber": 2,
              "venueMnemonic": "SHE",
              "raceType": "G",
              "startTime": "2026-04-16T00:59:00.000Z"
            }
          ],
          "poolTotal": 460.42,
          "jackpot": 0,
          "cominglingHost": "NSW",
          "cominglingHostName": "NSW TAB",
          "cominglingGuests": true,
          "substitute": "NR"
        },
        {
          "wageringProduct": "RunningDouble",
          "legNumber": 1,
          "poolStatusCode": "Closed",
          "cashOutEligibility": "Disabled",
          "legs": [
            {
              "legNumber": 1,
              "raceNumber": 2,
              "venueMnemonic": "SHE",
              "raceType": "G",
              "startTime": "2026-04-16T00:59:00.000Z"
            },
            {
              "legNumber": 2,
              "raceNumber": 3,
              "venueMnemonic": "SHE",
              "raceType": "G",
              "startTime": "2026-04-16T01:17:00.000Z"
            }
          ],
          "poolTotal": 0,
          "jackpot": 0,
          "cominglingHost": "NSW",
          "cominglingHostName": "NSW TAB",
          "cominglingGuests": true,
          "substitute": 2
        },
        {
          "wageringProduct": "EarlyQuaddie",
          "legNumber": 2,
          "poolStatusCode": "Closed",
          "cashOutEligibility": "Enabled",
          "legs": [
            {
              "legNumber": 1,
              "raceNumber": 1,
              "venueMnemonic": "SHE",
              "raceType": "G",
              "startTime": "2026-04-16T00:42:00.000Z"
            },
            {
              "legNumber": 2,
              "raceNumber": 2,
              "venueMnemonic": "SHE",
              "raceType": "G",
              "startTime": "2026-04-16T00:59:00.000Z"
            },
            {
              "legNumber": 3,
              "raceNumber": 3,
              "venueMnemonic": "SHE",
              "raceType": "G",
              "startTime": "2026-04-16T01:17:00.000Z"
            },
            {
              "legNumber": 4,
              "raceNumber": 4,
              "venueMnemonic": "SHE",
              "raceType": "G",
              "startTime": "2026-04-16T01:34:00.000Z"
            }
          ],
          "poolTotal": 0.09,
          "jackpot": 0,
          "cominglingHost": "NSW",
          "cominglingHostName": "NSW TAB",
          "cominglingGuests": true,
          "substitute": 2
        }
      ],
      "allowMulti": false,
      "allowParimutuelPlace": true,
      "parimutuelPlaceStatus": "Closed",
      "allowFixedOddsPlace": false,
      "numberOfPlaces": 2,
      "runners": [
        {
          "runnerName": "INDIANA ICON",
          "runnerNumber": 1,
          "fixedOdds": {
            "returnWin": 6,
            "returnWinTime": "2026-04-16T00:59:17.000Z",
            "returnWinOpen": 3.1,
            "returnWinOpenDaily": 3.1,
            "returnPlace": 2.4,
            "isFavouriteWin": false,
            "isFavouritePlace": false,
            "bettingStatus": "Placing",
            "propositionNumber": 166471,
            "differential": null,
            "flucs": [
              {
                "returnWin": 5.5,
                "returnWinTime": "2026-04-16T00:58:56.000Z"
              },
              {
                "returnWin": 5,
                "returnWinTime": "2026-04-16T00:58:13.000Z"
              },
              {
                "returnWin": 4.8,
                "returnWinTime": "2026-04-16T00:57:15.000Z"
              },
              {
                "returnWin": 4.4,
                "returnWinTime": "2026-04-16T00:56:13.000Z"
              }
            ],
            "returnHistory": [
              {
                "returnWin": 3.5,
                "returnWinTime": "2026-04-15T22:11:13.724Z"
              },
              {
                "returnWin": 3.1,
                "returnWinTime": "2026-04-15T21:27:17.598Z"
              },
              {
                "returnWin": 3.4,
                "returnWinTime": "2026-04-15T21:27:23.847Z"
              },
              {
                "returnWin": 3.6,
                "returnWinTime": "2026-04-16T00:51:07.953Z"
              },
              {
                "returnWin": 3.9,
                "returnWinTime": "2026-04-16T00:55:12.314Z"
              },
              {
                "returnWin": 4,
                "returnWinTime": "2026-04-16T00:55:49.132Z"
              },
              {
                "returnWin": 4.4,
                "returnWinTime": "2026-04-16T00:56:13.052Z"
              },
              {
                "returnWin": 4.8,
                "returnWinTime": "2026-04-16T00:57:14.781Z"
              },
              {
                "returnWin": 5,
                "returnWinTime": "2026-04-16T00:58:12.501Z"
              },
              {
                "returnWin": 5.5,
                "returnWinTime": "2026-04-16T00:58:55.684Z"
              },
              {
                "returnWin": 6,
                "returnWinTime": "2026-04-16T00:59:16.562Z"
              }
            ],
            "percentageChange": 9,
            "allowPlace": true
          },
          "parimutuel": {
            "returnWin": 6.3,
            "returnPlace": 2.7,
            "returnExact2": 0,
            "isFavouriteWin": false,
            "isFavouritePlace": false,
            "isFavouriteExact2": false,
            "bettingStatus": "Closed",
            "marketMovers": [
              {
                "returnWin": 6.3,
                "returnWinTime": "2026-04-16T00:59:48.000Z",
                "specialDisplayIndicator": false
              },
              {
                "returnWin": 6.3,
                "returnWinTime": "2026-04-16T00:59:22.000Z",
                "specialDisplayIndicator": false
              },
              {
                "returnWin": 6.2,
                "returnWinTime": "2026-04-16T00:58:37.000Z",
                "specialDisplayIndicator": false
              },
              {
                "returnWin": 5.6,
                "returnWinTime": "2026-04-16T00:57:52.000Z",
                "specialDisplayIndicator": false
              }
            ],
            "percentageChange": 0
          },
          "silkURL": "https://api.beta.tab.com.au/v1/tab-info-service/racing/silk/1",
          "trainerName": "M Sullivan",
          "vacantBox": false,
          "trainerFullName": "MARIEN SULLIVAN",
          "barrierNumber": 1,
          "riderDriverName": "",
          "riderDriverFullName": null,
          "handicapWeight": 0,
          "harnessHandicap": null,
          "blinkers": null,
          "claimAmount": -1,
          "last5Starts": "33455",
          "tcdwIndicators": "t d",
          "emergency": false,
          "penalty": null,
          "dfsFormRating": 88,
          "techFormRating": 0,
          "totalRatingPoints": 14,
          "earlySpeedRating": 52,
          "earlySpeedRatingBand": "MIDFIELD",
          "fastForm": [
            {
              "type": "TopRated",
              "keywords": null,
              "ranking": 3
            }
          ],
          "_links": {
            "form": "https://api.beta.tab.com.au/v1/tab-info-service/racing/dates/2026-04-16/meetings/G/SHE/races/2/form/1?jurisdiction=NSW"
          }
        },
        {
          "runnerName": "HARROW SWIFTY",
          "runnerNumber": 2,
          "fixedOdds": {
            "returnWin": 2.1,
            "returnWinTime": "2026-04-16T00:59:17.000Z",
            "returnWinOpen": 2.5,
            "returnWinOpenDaily": 2.5,
            "returnPlace": 1.35,
            "isFavouriteWin": false,
            "isFavouritePlace": false,
            "bettingStatus": "Loser",
            "propositionNumber": 166472,
            "differential": null,
            "flucs": [
              {
                "returnWin": 2.2,
                "returnWinTime": "2026-04-16T00:58:56.000Z"
              },
              {
                "returnWin": 2.4,
                "returnWinTime": "2026-04-16T00:58:13.000Z"
              },
              {
                "returnWin": 2.6,
                "returnWinTime": "2026-04-16T00:57:35.000Z"
              },
              {
                "returnWin": 2.7,
                "returnWinTime": "2026-04-16T00:57:16.000Z"
              }
            ],
            "returnHistory": [
              {
                "returnWin": 2.6,
                "returnWinTime": "2026-04-15T22:11:13.724Z"
              },
              {
                "returnWin": 2.5,
                "returnWinTime": "2026-04-15T21:27:17.598Z"
              },
              {
                "returnWin": 2.7,
                "returnWinTime": "2026-04-15T21:27:23.847Z"
              },
              {
                "returnWin": 2.7,
                "returnWinTime": "2026-04-16T00:49:10.555Z"
              },
              {
                "returnWin": 2.8,
                "returnWinTime": "2026-04-16T00:55:12.314Z"
              },
              {
                "returnWin": 2.7,
                "returnWinTime": "2026-04-16T00:56:13.052Z"
              },
              {
                "returnWin": 2.6,
                "returnWinTime": "2026-04-16T00:57:14.781Z"
              },
              {
                "returnWin": 2.7,
                "returnWinTime": "2026-04-16T00:57:15.825Z"
              },
              {
                "returnWin": 2.6,
                "returnWinTime": "2026-04-16T00:57:35.218Z"
              },
              {
                "returnWin": 2.4,
                "returnWinTime": "2026-04-16T00:58:12.501Z"
              },
              {
                "returnWin": 2.2,
                "returnWinTime": "2026-04-16T00:58:55.684Z"
              },
              {
                "returnWin": 2.1,
                "returnWinTime": "2026-04-16T00:59:16.562Z"
              }
            ],
            "percentageChange": -5,
            "allowPlace": true
          },
          "parimutuel": {
            "returnWin": 2.2,
            "returnPlace": 1.04,
            "returnExact2": 0,
            "isFavouriteWin": true,
            "isFavouritePlace": true,
            "isFavouriteExact2": false,
            "bettingStatus": "Closed",
            "marketMovers": [
              {
                "returnWin": 2.2,
                "returnWinTime": "2026-04-16T00:59:48.000Z",
                "specialDisplayIndicator": false
              },
              {
                "returnWin": 2.2,
                "returnWinTime": "2026-04-16T00:59:22.000Z",
                "specialDisplayIndicator": false
              },
              {
                "returnWin": 4.5,
                "returnWinTime": "2026-04-16T00:58:37.000Z",
                "specialDisplayIndicator": false
              },
              {
                "returnWin": 3.9,
                "returnWinTime": "2026-04-16T00:57:52.000Z",
                "specialDisplayIndicator": false
              },
              {
                "returnWin": 1.2,
                "returnWinTime": "2026-04-16T00:43:36.000Z",
                "specialDisplayIndicator": true
              }
            ],
            "percentageChange": 0
          },
          "silkURL": "https://api.beta.tab.com.au/v1/tab-info-service/racing/silk/2",
          "trainerName": "N Harris",
          "vacantBox": false,
          "trainerFullName": "NIKITA  HARRIS",
          "barrierNumber": 2,
          "riderDriverName": "",
          "riderDriverFullName": null,
          "handicapWeight": 0,
          "harnessHandicap": null,
          "blinkers": null,
          "claimAmount": -1,
          "last5Starts": "35644",
          "tcdwIndicators": null,
          "emergency": false,
          "penalty": null,
          "dfsFormRating": 100,
          "techFormRating": 0,
          "totalRatingPoints": 8,
          "earlySpeedRating": 56,
          "earlySpeedRatingBand": "MIDFIELD",
          "fastForm": [
            {
              "type": "LikelyLeader",
              "keywords": null,
              "ranking": null
            },
            {
              "type": "TopRated",
              "keywords": null,
              "ranking": 2
            }
          ],
          "_links": {
            "form": "https://api.beta.tab.com.au/v1/tab-info-service/racing/dates/2026-04-16/meetings/G/SHE/races/2/form/2?jurisdiction=NSW"
          }
        },
        {
          "runnerName": "....",
          "runnerNumber": 3,
          "fixedOdds": {
            "returnWin": null,
            "returnPlace": null,
            "isFavouriteWin": false,
            "isFavouritePlace": false,
            "bettingStatus": null,
            "propositionNumber": null,
            "differential": null,
            "returnHistory": [
              {
                "returnWin": null,
                "returnWinTime": null
              },
              {
                "returnWin": null,
                "returnWinTime": null
              },
              {
                "returnWin": null,
                "returnWinTime": null
              }
            ],
            "allowPlace": null
          },
          "parimutuel": {
            "returnWin": 0,
            "returnPlace": 0,
            "returnExact2": 0,
            "isFavouriteWin": false,
            "isFavouritePlace": false,
            "isFavouriteExact2": false,
            "bettingStatus": "Scratched"
          },
          "silkURL": "https://api.beta.tab.com.au/v1/tab-info-service/racing/silk/3",
          "trainerName": "",
          "vacantBox": true,
          "trainerFullName": null,
          "barrierNumber": 3,
          "riderDriverName": "",
          "riderDriverFullName": null,
          "handicapWeight": 0,
          "harnessHandicap": null,
          "blinkers": null,
          "claimAmount": -1,
          "last5Starts": null,
          "tcdwIndicators": null,
          "emergency": false,
          "penalty": null,
          "dfsFormRating": null,
          "techFormRating": 0,
          "totalRatingPoints": null,
          "earlySpeedRating": 0,
          "earlySpeedRatingBand": "BACKMARKER"
        },
        {
          "runnerName": "ACCIDENTAL",
          "runnerNumber": 4,
          "fixedOdds": {
            "returnWin": 3.4,
            "returnWinTime": "2026-04-16T00:59:17.000Z",
            "returnWinOpen": 2.6,
            "returnWinOpenDaily": 2.6,
            "returnPlace": 1.65,
            "isFavouriteWin": false,
            "isFavouritePlace": false,
            "bettingStatus": "Winner",
            "propositionNumber": 166474,
            "differential": null,
            "flucs": [
              {
                "returnWin": 3.3,
                "returnWinTime": "2026-04-16T00:58:56.000Z"
              },
              {
                "returnWin": 3,
                "returnWinTime": "2026-04-16T00:57:15.000Z"
              },
              {
                "returnWin": 2.9,
                "returnWinTime": "2026-04-16T00:56:13.000Z"
              },
              {
                "returnWin": 2.8,
                "returnWinTime": "2026-04-16T00:49:11.000Z"
              }
            ],
            "returnHistory": [
              {
                "returnWin": 2.9,
                "returnWinTime": "2026-04-15T22:11:13.724Z"
              },
              {
                "returnWin": 2.6,
                "returnWinTime": "2026-04-15T21:27:17.598Z"
              },
              {
                "returnWin": 2.7,
                "returnWinTime": "2026-04-15T21:27:23.847Z"
              },
              {
                "returnWin": 2.8,
                "returnWinTime": "2026-04-16T00:49:10.617Z"
              },
              {
                "returnWin": 2.9,
                "returnWinTime": "2026-04-16T00:56:13.052Z"
              },
              {
                "returnWin": 3,
                "returnWinTime": "2026-04-16T00:57:14.781Z"
              },
              {
                "returnWin": 3.3,
                "returnWinTime": "2026-04-16T00:58:55.684Z"
              },
              {
                "returnWin": 3.4,
                "returnWinTime": "2026-04-16T00:59:16.562Z"
              }
            ],
            "percentageChange": 3,
            "allowPlace": true
          },
          "parimutuel": {
            "returnWin": 2.8,
            "returnPlace": 1.9,
            "returnExact2": 0,
            "isFavouriteWin": false,
            "isFavouritePlace": false,
            "isFavouriteExact2": false,
            "bettingStatus": "Closed",
            "marketMovers": [
              {
                "returnWin": 2.8,
                "returnWinTime": "2026-04-16T00:59:48.000Z",
                "specialDisplayIndicator": false
              },
              {
                "returnWin": 2.8,
                "returnWinTime": "2026-04-16T00:59:22.000Z",
                "specialDisplayIndicator": false
              },
              {
                "returnWin": 2.9,
                "returnWinTime": "2026-04-16T00:58:37.000Z",
                "specialDisplayIndicator": false
              },
              {
                "returnWin": 4,
                "returnWinTime": "2026-04-16T00:57:52.000Z",
                "specialDisplayIndicator": false
              },
              {
                "returnWin": 3.6,
                "returnWinTime": "2026-04-16T00:43:36.000Z",
                "specialDisplayIndicator": true
              }
            ],
            "percentageChange": 0
          },
          "silkURL": "https://api.beta.tab.com.au/v1/tab-info-service/racing/silk/4",
          "trainerName": "R Camilleri",
          "vacantBox": false,
          "trainerFullName": "ROBERT CAMILLERI",
          "barrierNumber": 4,
          "riderDriverName": "",
          "riderDriverFullName": null,
          "handicapWeight": 0,
          "harnessHandicap": null,
          "blinkers": null,
          "claimAmount": -1,
          "last5Starts": "32577",
          "tcdwIndicators": "t d",
          "emergency": false,
          "penalty": null,
          "dfsFormRating": 85,
          "techFormRating": 0,
          "totalRatingPoints": 14,
          "earlySpeedRating": 49,
          "earlySpeedRatingBand": "MIDFIELD",
          "fastForm": [
            {
              "type": "TopRated",
              "keywords": null,
              "ranking": 1
            }
          ],
          "_links": {
            "form": "https://api.beta.tab.com.au/v1/tab-info-service/racing/dates/2026-04-16/meetings/G/SHE/races/2/form/4?jurisdiction=NSW"
          }
        },
        {
          "runnerName": "....",
          "runnerNumber": 5,
          "fixedOdds": {
            "returnWin": null,
            "returnPlace": null,
            "isFavouriteWin": false,
            "isFavouritePlace": false,
            "bettingStatus": null,
            "propositionNumber": null,
            "differential": null,
            "returnHistory": [
              {
                "returnWin": null,
                "returnWinTime": null
              },
              {
                "returnWin": null,
                "returnWinTime": null
              },
              {
                "returnWin": null,
                "returnWinTime": null
              }
            ],
            "allowPlace": null
          },
          "parimutuel": {
            "returnWin": 0,
            "returnPlace": 0,
            "returnExact2": 0,
            "isFavouriteWin": false,
            "isFavouritePlace": false,
            "isFavouriteExact2": false,
            "bettingStatus": "Scratched"
          },
          "silkURL": "https://api.beta.tab.com.au/v1/tab-info-service/racing/silk/5",
          "trainerName": "",
          "vacantBox": true,
          "trainerFullName": null,
          "barrierNumber": 5,
          "riderDriverName": "",
          "riderDriverFullName": null,
          "handicapWeight": 0,
          "harnessHandicap": null,
          "blinkers": null,
          "claimAmount": -1,
          "last5Starts": null,
          "tcdwIndicators": null,
          "emergency": false,
          "penalty": null,
          "dfsFormRating": null,
          "techFormRating": 0,
          "totalRatingPoints": null,
          "earlySpeedRating": 0,
          "earlySpeedRatingBand": "BACKMARKER"
        },
        {
          "runnerName": "SLICK STRIKE",
          "runnerNumber": 6,
          "fixedOdds": {
            "returnWin": 4.2,
            "returnWinTime": "2026-04-16T00:58:13.000Z",
            "returnWinOpen": 10,
            "returnWinOpenDaily": 10,
            "returnPlace": 1.85,
            "isFavouriteWin": false,
            "isFavouritePlace": false,
            "bettingStatus": "Loser",
            "propositionNumber": 166476,
            "differential": null,
            "flucs": [
              {
                "returnWin": 4,
                "returnWinTime": "2026-04-16T00:56:41.000Z"
              },
              {
                "returnWin": 4.2,
                "returnWinTime": "2026-04-16T00:56:13.000Z"
              },
              {
                "returnWin": 4.6,
                "returnWinTime": "2026-04-16T00:55:49.000Z"
              },
              {
                "returnWin": 5,
                "returnWinTime": "2026-04-15T21:27:24.000Z"
              }
            ],
            "returnHistory": [
              {
                "returnWin": 10,
                "returnWinTime": "2026-04-15T21:27:17.598Z"
              },
              {
                "returnWin": 5,
                "returnWinTime": "2026-04-15T21:27:23.847Z"
              },
              {
                "returnWin": 4.6,
                "returnWinTime": "2026-04-16T00:55:49.132Z"
              },
              {
                "returnWin": 4.2,
                "returnWinTime": "2026-04-16T00:56:13.052Z"
              },
              {
                "returnWin": 4,
                "returnWinTime": "2026-04-16T00:56:40.515Z"
              },
              {
                "returnWin": 4.2,
                "returnWinTime": "2026-04-16T00:58:12.501Z"
              }
            ],
            "percentageChange": 5,
            "allowPlace": true
          },
          "parimutuel": {
            "returnWin": 5.2,
            "returnPlace": 2.6,
            "returnExact2": 0,
            "isFavouriteWin": false,
            "isFavouritePlace": false,
            "isFavouriteExact2": false,
            "bettingStatus": "Closed",
            "marketMovers": [
              {
                "returnWin": 5.2,
                "returnWinTime": "2026-04-16T00:59:48.000Z",
                "specialDisplayIndicator": false
              },
              {
                "returnWin": 5.2,
                "returnWinTime": "2026-04-16T00:59:22.000Z",
                "specialDisplayIndicator": false
              },
              {
                "returnWin": 2.4,
                "returnWinTime": "2026-04-16T00:58:37.000Z",
                "specialDisplayIndicator": false
              },
              {
                "returnWin": 2.2,
                "returnWinTime": "2026-04-16T00:57:52.000Z",
                "specialDisplayIndicator": false
              },
              {
                "returnWin": 12.8,
                "returnWinTime": "2026-04-16T00:43:36.000Z",
                "specialDisplayIndicator": true
              }
            ],
            "percentageChange": 0
          },
          "silkURL": "https://api.beta.tab.com.au/v1/tab-info-service/racing/silk/6",
          "trainerName": "S Kemp",
          "vacantBox": false,
          "trainerFullName": "STEVEN KEMP",
          "barrierNumber": 6,
          "riderDriverName": "",
          "riderDriverFullName": null,
          "handicapWeight": 0,
          "harnessHandicap": null,
          "blinkers": null,
          "claimAmount": -1,
          "last5Starts": "f7x86",
          "tcdwIndicators": null,
          "emergency": false,
          "penalty": null,
          "dfsFormRating": 20,
          "techFormRating": 0,
          "totalRatingPoints": 0,
          "earlySpeedRating": 100,
          "earlySpeedRatingBand": "LEADER",
          "_links": {
            "form": "https://api.beta.tab.com.au/v1/tab-info-service/racing/dates/2026-04-16/meetings/G/SHE/races/2/form/6?jurisdiction=NSW"
          }
        },
        {
          "runnerName": "....",
          "runnerNumber": 7,
          "fixedOdds": {
            "returnWin": null,
            "returnPlace": null,
            "isFavouriteWin": false,
            "isFavouritePlace": false,
            "bettingStatus": null,
            "propositionNumber": null,
            "differential": null,
            "returnHistory": [
              {
                "returnWin": null,
                "returnWinTime": null
              },
              {
                "returnWin": null,
                "returnWinTime": null
              },
              {
                "returnWin": null,
                "returnWinTime": null
              }
            ],
            "allowPlace": null
          },
          "parimutuel": {
            "returnWin": 0,
            "returnPlace": 0,
            "returnExact2": 0,
            "isFavouriteWin": false,
            "isFavouritePlace": false,
            "isFavouriteExact2": false,
            "bettingStatus": "Scratched"
          },
          "silkURL": "https://api.beta.tab.com.au/v1/tab-info-service/racing/silk/7",
          "trainerName": "",
          "vacantBox": true,
          "trainerFullName": null,
          "barrierNumber": 7,
          "riderDriverName": "",
          "riderDriverFullName": null,
          "handicapWeight": 0,
          "harnessHandicap": null,
          "blinkers": null,
          "claimAmount": -1,
          "last5Starts": null,
          "tcdwIndicators": null,
          "emergency": false,
          "penalty": null,
          "dfsFormRating": null,
          "techFormRating": 0,
          "totalRatingPoints": null,
          "earlySpeedRating": 0,
          "earlySpeedRatingBand": "BACKMARKER"
        },
        {
          "runnerName": "TOOTHPICK",
          "runnerNumber": 8,
          "fixedOdds": {
            "returnWin": 51,
            "returnWinTime": "2026-04-16T00:58:13.000Z",
            "returnWinOpen": 19,
            "returnWinOpenDaily": 19,
            "returnPlace": 15,
            "isFavouriteWin": false,
            "isFavouritePlace": false,
            "bettingStatus": "Loser",
            "propositionNumber": 166478,
            "differential": null,
            "flucs": [
              {
                "returnWin": 41,
                "returnWinTime": "2026-04-16T00:57:15.000Z"
              },
              {
                "returnWin": 31,
                "returnWinTime": "2026-04-16T00:56:13.000Z"
              },
              {
                "returnWin": 23,
                "returnWinTime": "2026-04-16T00:55:12.000Z"
              },
              {
                "returnWin": 21,
                "returnWinTime": "2026-04-16T00:51:08.000Z"
              }
            ],
            "returnHistory": [
              {
                "returnWin": 21,
                "returnWinTime": "2026-04-15T22:11:13.724Z"
              },
              {
                "returnWin": 19,
                "returnWinTime": "2026-04-15T21:27:17.598Z"
              },
              {
                "returnWin": 23,
                "returnWinTime": "2026-04-15T21:27:23.847Z"
              },
              {
                "returnWin": 19,
                "returnWinTime": "2026-04-16T00:44:06.154Z"
              },
              {
                "returnWin": 21,
                "returnWinTime": "2026-04-16T00:51:07.953Z"
              },
              {
                "returnWin": 23,
                "returnWinTime": "2026-04-16T00:55:12.314Z"
              },
              {
                "returnWin": 31,
                "returnWinTime": "2026-04-16T00:56:13.052Z"
              },
              {
                "returnWin": 41,
                "returnWinTime": "2026-04-16T00:57:14.781Z"
              },
              {
                "returnWin": 51,
                "returnWinTime": "2026-04-16T00:58:12.501Z"
              }
            ],
            "percentageChange": 24,
            "allowPlace": true
          },
          "parimutuel": {
            "returnWin": 66.1,
            "returnPlace": 0,
            "returnExact2": 0,
            "isFavouriteWin": false,
            "isFavouritePlace": false,
            "isFavouriteExact2": false,
            "bettingStatus": "Closed",
            "marketMovers": [
              {
                "returnWin": 66.1,
                "returnWinTime": "2026-04-16T00:59:48.000Z",
                "specialDisplayIndicator": false
              },
              {
                "returnWin": 66.1,
                "returnWinTime": "2026-04-16T00:59:22.000Z",
                "specialDisplayIndicator": false
              },
              {
                "returnWin": 24,
                "returnWinTime": "2026-04-16T00:58:37.000Z",
                "specialDisplayIndicator": false
              },
              {
                "returnWin": 19.2,
                "returnWinTime": "2026-04-16T00:57:52.000Z",
                "specialDisplayIndicator": false
              },
              {
                "returnWin": 25.6,
                "returnWinTime": "2026-04-16T00:43:36.000Z",
                "specialDisplayIndicator": true
              }
            ],
            "percentageChange": 0
          },
          "silkURL": "https://api.beta.tab.com.au/v1/tab-info-service/racing/silk/8",
          "trainerName": "J Mangion",
          "vacantBox": false,
          "trainerFullName": "JOHN MANGION",
          "barrierNumber": 8,
          "riderDriverName": "",
          "riderDriverFullName": null,
          "handicapWeight": 0,
          "harnessHandicap": null,
          "blinkers": null,
          "claimAmount": -1,
          "last5Starts": "77658",
          "tcdwIndicators": "t d",
          "emergency": false,
          "penalty": null,
          "dfsFormRating": 81,
          "techFormRating": 0,
          "totalRatingPoints": 0,
          "earlySpeedRating": 23,
          "earlySpeedRatingBand": "BACKMARKER",
          "_links": {
            "form": "https://api.beta.tab.com.au/v1/tab-info-service/racing/dates/2026-04-16/meetings/G/SHE/races/2/form/8?jurisdiction=NSW"
          }
        }
      ],
      "oddsUpdateTime": "2026-04-16T01:00:55.000Z",
      "fixedOddsUpdateTime": "2026-04-16T00:59:17.000Z",
      "raceComments": "{\"comment\":\"4. ACCIDENTAL is overdue for a maiden success having placed at six of 16 starts, the latest missing the frame when seventh at this track. Better than last start and worth following up. 2. HARROW SWIFTY showed little early speed at her last couple, the latest finishing fourth (22.92) in a Maiden at Ballarat. One of the main contenders. 1. INDIANA ICON comes off a moderate effort last start, finishing fifth at this track over 390m behind Limosa (23.32). Worth following up. 6. SLICK STRIKE is worth a look despite no experience at this circuit.\",\"runners\":[4,2,1,6],\"exclusive\":false}",
      "tips": {
        "tipType": "Standard",
        "tipster": "Patrick Doyle",
        "tipRunnerNumbers": [
          2,
          4,
          6,
          8
        ]
      },
      "ratings": [
        {
          "ratingType": "Rating",
          "ratingRunnerNumbers": [
            2,
            1,
            4,
            8
          ]
        },
        {
          "ratingType": "Last12Months",
          "ratingRunnerNumbers": [
            4,
            1,
            2,
            6
          ]
        },
        {
          "ratingType": "Recent",
          "ratingRunnerNumbers": [
            4,
            1,
            2,
            6
          ]
        },
        {
          "ratingType": "Distance",
          "ratingRunnerNumbers": [
            4,
            1,
            2,
            8
          ]
        },
        {
          "ratingType": "Class",
          "ratingRunnerNumbers": [
            4,
            1,
            2,
            8
          ]
        },
        {
          "ratingType": "Time",
          "ratingRunnerNumbers": [
            1,
            2,
            4,
            6
          ]
        },
        {
          "ratingType": "Overall",
          "ratingRunnerNumbers": [
            4,
            1,
            2,
            6
          ]
        }
      ],
      "dividends": [
        {
          "wageringProduct": "Win",
          "poolStatusCode": "Closed",
          "countBackLevelDescription": null,
          "jackpotCarriedOver": 0,
          "poolDividends": [
            {
              "selections": [
                4
              ],
              "amount": 2.8
            }
          ]
        },
        {
          "wageringProduct": "Place",
          "poolStatusCode": "Closed",
          "countBackLevelDescription": null,
          "jackpotCarriedOver": 0,
          "poolDividends": [
            {
              "selections": [
                4
              ],
              "amount": 1.9
            },
            {
              "selections": [
                1
              ],
              "amount": 2.7
            }
          ]
        },
        {
          "wageringProduct": "Quinella",
          "poolStatusCode": "Closed",
          "countBackLevelDescription": null,
          "jackpotCarriedOver": 0,
          "poolDividends": [
            {
              "selections": [
                4,
                1
              ],
              "amount": 8.7
            }
          ]
        },
        {
          "wageringProduct": "Exacta",
          "poolStatusCode": "Closed",
          "countBackLevelDescription": null,
          "jackpotCarriedOver": 0,
          "poolDividends": [
            {
              "selections": [
                4,
                1
              ],
              "amount": 10.1
            }
          ]
        },
        {
          "wageringProduct": "Duet",
          "poolStatusCode": "Closed",
          "countBackLevelDescription": null,
          "jackpotCarriedOver": 0,
          "poolDividends": [
            {
              "selections": [
                "F",
                "F"
              ],
              "amount": 0
            }
          ]
        },
        {
          "wageringProduct": "Trifecta",
          "poolStatusCode": "Closed",
          "countBackLevelDescription": null,
          "jackpotCarriedOver": 0,
          "poolDividends": [
            {
              "selections": [
                4,
                1,
                6
              ],
              "amount": 71.1
            }
          ]
        },
        {
          "wageringProduct": "FirstFour",
          "poolStatusCode": "Closed",
          "countBackLevelDescription": null,
          "jackpotCarriedOver": 0,
          "poolDividends": [
            {
              "selections": [
                4,
                1,
                6,
                2
              ],
              "amount": 74.4
            }
          ]
        },
        {
          "wageringProduct": "RunningDouble",
          "poolStatusCode": "Closed",
          "countBackLevelDescription": null,
          "jackpotCarriedOver": 0,
          "poolDividends": [
            {
              "selections": [
                8,
                4
              ],
              "amount": 21.2
            }
          ]
        }
      ],
      "multiLegApproximates": [
        {
          "wageringProduct": "RunningDouble",
          "approximateSets": [
            {
              "results": [
                {
                  "legNumber": 1,
                  "result": 8,
                  "runnerName": "KRAKEN SANDY"
                }
              ],
              "approximates": [
                {
                  "selection": 1,
                  "return": 21.3
                },
                {
                  "selection": 2,
                  "return": 15.5
                },
                {
                  "selection": 3,
                  "return": 0
                },
                {
                  "selection": 4,
                  "return": 21.2
                },
                {
                  "selection": 5,
                  "return": 0
                },
                {
                  "selection": 6,
                  "return": 31
                },
                {
                  "selection": 7,
                  "return": 0
                },
                {
                  "selection": 8,
                  "return": 80.8
                }
              ]
            }
          ]
        }
      ],
      "betTypes": [],
      "extraMarkets": [
        {
          "id": 131962736,
          "name": "SHEPPARTON-R2-Fav Out",
          "shortName": "SHEPPARTON-R2-FavOut",
          "betOption": "Favourite Out",
          "message": "Must finish 1st or 2nd behind N/A Runner",
          "informationMessage": null,
          "cashOutEligibility": "Disabled",
          "refundsAndDeductions": true,
          "closeTime": "2026-04-16T00:59:00.000Z",
          "bettingStatus": "Resulted",
          "allowWin": true,
          "allowPlace": false,
          "allowEachWay": false,
          "allowMulti": true,
          "allowMultiWin": true,
          "allowMultiPlace": false,
          "allowMultiEachWay": false,
          "numberOfPlaces": 0,
          "allowBundle": false,
          "propositions": [
            {
              "id": "4551647",
              "name": "INDIANA ICON",
              "returnWin": 3.6,
              "returnPlace": 1.01,
              "bettingStatus": "Loser",
              "allowPlace": false,
              "sortOrder": 1,
              "number": 150001,
              "runnerNumber": 1,
              "isOpen": false,
              "silkURL": "https://api.beta.tab.com.au/v1/tab-info-service/racing/silk/1",
              "_links": {
                "form": "https://api.beta.tab.com.au/v1/tab-info-service/racing/dates/2026-04-16/meetings/G/SHE/races/2/form/1?jurisdiction=NSW"
              }
            },
            {
              "id": "4551648",
              "name": "HARROW SWIFTY",
              "returnWin": 1.01,
              "returnPlace": 1.01,
              "bettingStatus": "Loser",
              "allowPlace": false,
              "sortOrder": 2,
              "number": 150005,
              "runnerNumber": 2,
              "isOpen": false,
              "silkURL": "https://api.beta.tab.com.au/v1/tab-info-service/racing/silk/2",
              "_links": {
                "form": "https://api.beta.tab.com.au/v1/tab-info-service/racing/dates/2026-04-16/meetings/G/SHE/races/2/form/2?jurisdiction=NSW"
              }
            },
            {
              "id": "4551649",
              "name": "ACCIDENTAL",
              "returnWin": 2,
              "returnPlace": 1.01,
              "bettingStatus": "Winner",
              "allowPlace": false,
              "sortOrder": 3,
              "number": 150010,
              "runnerNumber": 4,
              "isOpen": false,
              "silkURL": "https://api.beta.tab.com.au/v1/tab-info-service/racing/silk/4",
              "_links": {
                "form": "https://api.beta.tab.com.au/v1/tab-info-service/racing/dates/2026-04-16/meetings/G/SHE/races/2/form/4?jurisdiction=NSW"
              }
            },
            {
              "id": "4551650",
              "name": "SLICK STRIKE",
              "returnWin": 2.5,
              "returnPlace": 1.01,
              "bettingStatus": "Loser",
              "allowPlace": false,
              "sortOrder": 4,
              "number": 150017,
              "runnerNumber": 6,
              "isOpen": false,
              "silkURL": "https://api.beta.tab.com.au/v1/tab-info-service/racing/silk/6",
              "_links": {
                "form": "https://api.beta.tab.com.au/v1/tab-info-service/racing/dates/2026-04-16/meetings/G/SHE/races/2/form/6?jurisdiction=NSW"
              }
            },
            {
              "id": "4551651",
              "name": "TOOTHPICK",
              "returnWin": 26,
              "returnPlace": 1.01,
              "bettingStatus": "Loser",
              "allowPlace": false,
              "sortOrder": 5,
              "number": 150028,
              "runnerNumber": 8,
              "isOpen": false,
              "silkURL": "https://api.beta.tab.com.au/v1/tab-info-service/racing/silk/8",
              "_links": {
                "form": "https://api.beta.tab.com.au/v1/tab-info-service/racing/dates/2026-04-16/meetings/G/SHE/races/2/form/8?jurisdiction=NSW"
              }
            }
          ]
        }
      ]
    }
  }
}