{"data":{"raceNumber":10,"raceName":"WEBBCON MARINE","raceStartTime":"2026-04-14T08:04:00+00:00","raceStatus":"Paying","raceDistance":410,"results":[[5],[8],[4],[1]],"resultedTime":"2026-04-14T08:05:50+00:00","substitute":2,"scratchings":[{"runnerName":"....","runnerNumber":3,"finishingPosition":0,"trainerName":null,"barrierNumber":3,"riderDriverName":"","claimAmount":0,"fixedOdds":{},"parimutuel":{"bettingStatus":"Scratched","returnWin":0,"returnPlace":0}},{"runnerName":"....","runnerNumber":6,"finishingPosition":0,"trainerName":null,"barrierNumber":6,"riderDriverName":"","claimAmount":0,"fixedOdds":{},"parimutuel":{"bettingStatus":"Scratched","returnWin":0,"returnPlace":0}}],"runners":[{"runnerName":"OTTO RHODE","runnerNumber":1,"finishingPosition":4,"trainerName":"GARRY GEORGE","barrierNumber":1,"riderDriverName":"","claimAmount":0,"fixedOdds":{"returnWin":3.9,"returnWinOpen":9,"returnPlace":1.95,"bettingStatus":"Loser","winDeduction":0,"placeDeduction":0,"propositionNumber":154611,"scratchedTime":null},"parimutuel":{"bettingStatus":"Normal","returnWin":4.3,"returnPlace":1.6}},{"runnerName":"TIME PERPETUATED","runnerNumber":2,"finishingPosition":0,"trainerName":"RODNEY CLARK","barrierNumber":2,"riderDriverName":"","claimAmount":0,"fixedOdds":{"returnWin":2.8,"returnWinOpen":2,"returnPlace":1.6,"bettingStatus":"Loser","winDeduction":0,"placeDeduction":0,"propositionNumber":154612,"scratchedTime":null},"parimutuel":{"bettingStatus":"Normal","returnWin":3.2,"returnPlace":1.5}},{"runnerName":"....","runnerNumber":3,"finishingPosition":0,"trainerName":null,"barrierNumber":3,"riderDriverName":"","claimAmount":0,"fixedOdds":{},"parimutuel":{"bettingStatus":"Scratched","returnWin":0,"returnPlace":0}},{"runnerName":"JUNO USKO","runnerNumber":4,"finishingPosition":3,"trainerName":"JONATHON MALONE","barrierNumber":4,"riderDriverName":"","claimAmount":0,"fixedOdds":{"returnWin":14,"returnWinOpen":7.5,"returnPlace":5,"bettingStatus":"Loser","winDeduction":0,"placeDeduction":0,"propositionNumber":154614,"scratchedTime":null},"parimutuel":{"bettingStatus":"Normal","returnWin":10.7,"returnPlace":5.1}},{"runnerName":"MAXIMUM SUNSET","runnerNumber":5,"finishingPosition":1,"trainerName":"JORDAN COOPER","barrierNumber":5,"riderDriverName":"","claimAmount":0,"fixedOdds":{"returnWin":3.9,"returnWinOpen":4.2,"returnPlace":1.95,"bettingStatus":"Winner","winDeduction":0,"placeDeduction":0,"propositionNumber":154615,"scratchedTime":null},"parimutuel":{"bettingStatus":"Normal","returnWin":4.1,"returnPlace":2.3}},{"runnerName":"....","runnerNumber":6,"finishingPosition":0,"trainerName":null,"barrierNumber":6,"riderDriverName":"","claimAmount":0,"fixedOdds":{},"parimutuel":{"bettingStatus":"Scratched","returnWin":0,"returnPlace":0}},{"runnerName":"DREAM LUCKY","runnerNumber":7,"finishingPosition":0,"trainerName":"CHLOE DEW","barrierNumber":7,"riderDriverName":"","claimAmount":0,"fixedOdds":{"returnWin":61,"returnWinOpen":9.5,"returnPlace":17,"bettingStatus":"Loser","winDeduction":0,"placeDeduction":0,"propositionNumber":154617,"scratchedTime":null},"parimutuel":{"bettingStatus":"Normal","returnWin":18.5,"returnPlace":18.7}},{"runnerName":"ZIPPING WICHITA","runnerNumber":8,"finishingPosition":2,"trainerName":"MATTHEW LANIGAN","barrierNumber":8,"riderDriverName":"","claimAmount":0,"fixedOdds":{"returnWin":3.9,"returnWinOpen":4.6,"returnPlace":1.95,"bettingStatus":"Placing","winDeduction":0,"placeDeduction":0,"propositionNumber":154618,"scratchedTime":null},"parimutuel":{"bettingStatus":"Normal","returnWin":4.1,"returnPlace":2.4}}],"raceClassConditions":"Mixed 6/7","hasFixedOdds":false,"hasParimutuel":true,"winBook":"http://internal-aviato-lb-212286492.ap-southeast-2.elb.amazonaws.com/historical-results/v4/TabcorpNSW/fixedodds/2026/4/14/book/GVHRHORSW9/propositions","willHaveFixedOdds":true,"meeting":{"meetingDate":"2026-04-14","location":"VIC","meetingName":"HORSHAM","raceType":"G","venueMnemonic":"P","sellCode":{"meetingCode":"P","scheduledType":"G"}},"skyRacing":{"audio":"https://mediatabs.skyracing.com.au/Audio_Replay/2026/04/20260414HXGG10.mp3","video":"https://mediatabs.skyracing.com.au/Race_Replay/2026/04/20260414HXGG10_V.mp4"},"pools":[{"poolStatusCode":"Paying","wageringProduct":"Win","poolTotal":2149.88,"jackpot":0,"poolCloseTime":"2026-04-14T08:04:40+00:00","legs":[{"legNumber":1,"raceNumber":10,"venueMnemonic":"P","raceType":"G","startTime":"2026-04-14T08:04:00+00:00"}]},{"poolStatusCode":"Paying","wageringProduct":"Place","poolTotal":415.04,"jackpot":0,"poolCloseTime":"2026-04-14T08:04:40+00:00","legs":[{"legNumber":1,"raceNumber":10,"venueMnemonic":"P","raceType":"G","startTime":"2026-04-14T08:04:00+00:00"}]},{"poolStatusCode":"Paying","wageringProduct":"Quinella","poolTotal":960.13,"jackpot":0,"poolCloseTime":"2026-04-14T08:04:40+00:00","legs":[{"legNumber":1,"raceNumber":10,"venueMnemonic":"P","raceType":"G","startTime":"2026-04-14T08:04:00+00:00"}]},{"poolStatusCode":"Paying","wageringProduct":"Exacta","poolTotal":465.55,"jackpot":0,"poolCloseTime":"2026-04-14T08:04:40+00:00","legs":[{"legNumber":1,"raceNumber":10,"venueMnemonic":"P","raceType":"G","startTime":"2026-04-14T08:04:00+00:00"}]},{"poolStatusCode":"Paying","wageringProduct":"Duet","poolTotal":0,"jackpot":0,"poolCloseTime":"2026-04-13T22:35:14+00:00","legs":[{"legNumber":1,"raceNumber":10,"venueMnemonic":"P","raceType":"G","startTime":"2026-04-14T08:04:00+00:00"}]},{"poolStatusCode":"Paying","wageringProduct":"Trifecta","poolTotal":1632.82,"jackpot":0,"poolCloseTime":"2026-04-14T08:04:40+00:00","legs":[{"legNumber":1,"raceNumber":10,"venueMnemonic":"P","raceType":"G","startTime":"2026-04-14T08:04:00+00:00"}]},{"poolStatusCode":"Paying","wageringProduct":"FirstFour","poolTotal":1397.14,"jackpot":0,"poolCloseTime":"2026-04-14T08:04:40+00:00","legs":[{"legNumber":1,"raceNumber":10,"venueMnemonic":"P","raceType":"G","startTime":"2026-04-14T08:04:00+00:00"}]},{"poolStatusCode":"Paying","wageringProduct":"RunningDouble","poolTotal":7.1,"jackpot":0,"poolCloseTime":"2026-04-14T08:04:40+00:00","legs":[{"legNumber":1,"raceNumber":10,"venueMnemonic":"P","raceType":"G","startTime":"2026-04-14T08:04:00+00:00"},{"legNumber":2,"raceNumber":11,"venueMnemonic":"P","raceType":"G","startTime":"2026-04-14T08:22:00+00:00"}]}],"dividends":[{"poolStatusCode":"Paying","wageringProduct":"Win","jackpotCarriedOver":0,"poolCloseTime":"2026-04-14T08:04:40+00:00","poolDividends":[{"selections":[5],"amount":4.1}]},{"poolStatusCode":"Paying","wageringProduct":"Place","jackpotCarriedOver":0,"poolCloseTime":"2026-04-14T08:04:40+00:00","poolDividends":[{"selections":[5],"amount":2.3},{"selections":[8],"amount":2.4}]},{"poolStatusCode":"Paying","wageringProduct":"Quinella","jackpotCarriedOver":0,"poolCloseTime":"2026-04-14T08:04:40+00:00","poolDividends":[{"selections":[5,8],"amount":10}]},{"poolStatusCode":"Paying","wageringProduct":"Exacta","jackpotCarriedOver":0,"poolCloseTime":"2026-04-14T08:04:40+00:00","poolDividends":[{"selections":[5,8],"amount":9.3}]},{"poolStatusCode":"Paying","wageringProduct":"Duet","jackpotCarriedOver":0,"poolCloseTime":"2026-04-13T22:35:14+00:00","poolDividends":[{"selections":["F","F"],"amount":0}]},{"poolStatusCode":"Paying","wageringProduct":"Trifecta","jackpotCarriedOver":0,"poolCloseTime":"2026-04-14T08:04:40+00:00","poolDividends":[{"selections":[5,8,4],"amount":101.8}]},{"poolStatusCode":"Paying","wageringProduct":"FirstFour","jackpotCarriedOver":0,"poolCloseTime":"2026-04-14T08:04:40+00:00","poolDividends":[{"selections":[5,8,4,1],"amount":311.6}]},{"poolStatusCode":"Paying","wageringProduct":"RunningDouble","jackpotCarriedOver":0,"poolCloseTime":"2026-04-14T07:40:25+00:00","poolDividends":[{"selections":[1,5],"amount":0}]}]}}