{
  "data": {
    "raceNumber": 1,
    "raceName": "METAL WORX MAIDEN STAKE",
    "raceStartTime": "2026-04-19T02:35:00+00:00",
    "raceStatus": "Paying",
    "raceDistance": 305,
    "results": [
      [
        1
      ],
      [
        8
      ],
      [
        2
      ],
      [
        6
      ]
    ],
    "resultedTime": "2026-04-19T02:37:24+00:00",
    "substitute": 2,
    "scratchings": [
      {
        "runnerName": "....",
        "runnerNumber": 3,
        "finishingPosition": 0,
        "trainerName": null,
        "barrierNumber": 3,
        "riderDriverName": "",
        "claimAmount": 0,
        "fixedOdds": {},
        "parimutuel": {
          "bettingStatus": "Scratched",
          "returnWin": 0,
          "returnPlace": 0
        }
      },
      {
        "runnerName": "SATIN SADIE",
        "runnerNumber": 4,
        "finishingPosition": 0,
        "trainerName": "ROSALYN HUME",
        "barrierNumber": 4,
        "riderDriverName": "",
        "claimAmount": 0,
        "fixedOdds": {
          "returnWin": 1.01,
          "returnWinOpen": 0,
          "returnPlace": 0,
          "bettingStatus": "LateScratched",
          "winDeduction": 0,
          "placeDeduction": 0,
          "propositionNumber": 160134,
          "scratchedTime": "2026-04-18T05:36:22+00:00"
        },
        "parimutuel": {
          "bettingStatus": "Scratched",
          "returnWin": 0,
          "returnPlace": 0
        }
      },
      {
        "runnerName": "....",
        "runnerNumber": 5,
        "finishingPosition": 0,
        "trainerName": null,
        "barrierNumber": 5,
        "riderDriverName": "",
        "claimAmount": 0,
        "fixedOdds": {},
        "parimutuel": {
          "bettingStatus": "Scratched",
          "returnWin": 0,
          "returnPlace": 0
        }
      },
      {
        "runnerName": "....",
        "runnerNumber": 7,
        "finishingPosition": 0,
        "trainerName": null,
        "barrierNumber": 7,
        "riderDriverName": "",
        "claimAmount": 0,
        "fixedOdds": {},
        "parimutuel": {
          "bettingStatus": "Scratched",
          "returnWin": 0,
          "returnPlace": 0
        }
      }
    ],
    "runners": [
      {
        "runnerName": "WHAT ODDS BILLY",
        "runnerNumber": 1,
        "finishingPosition": 1,
        "trainerName": "APRIL JANSSEN",
        "barrierNumber": 1,
        "riderDriverName": "",
        "claimAmount": 0,
        "fixedOdds": {
          "returnWin": 9,
          "returnWinOpen": 13,
          "returnPlace": 2.9,
          "bettingStatus": "Winner",
          "winDeduction": 0,
          "placeDeduction": 0,
          "propositionNumber": 160131,
          "scratchedTime": null
        },
        "parimutuel": {
          "bettingStatus": "Normal",
          "returnWin": 5.8,
          "returnPlace": 1.04
        }
      },
      {
        "runnerName": "SWIFT GENO",
        "runnerNumber": 2,
        "finishingPosition": 3,
        "trainerName": "ROSALYN HUME",
        "barrierNumber": 2,
        "riderDriverName": "",
        "claimAmount": 0,
        "fixedOdds": {
          "returnWin": 2.4,
          "returnWinOpen": 2.5,
          "returnPlace": 1.35,
          "bettingStatus": "Loser",
          "winDeduction": 0,
          "placeDeduction": 0,
          "propositionNumber": 160132,
          "scratchedTime": null
        },
        "parimutuel": {
          "bettingStatus": "Normal",
          "returnWin": 2.2,
          "returnPlace": 0
        }
      },
      {
        "runnerName": "....",
        "runnerNumber": 3,
        "finishingPosition": 0,
        "trainerName": null,
        "barrierNumber": 3,
        "riderDriverName": "",
        "claimAmount": 0,
        "fixedOdds": {},
        "parimutuel": {
          "bettingStatus": "Scratched",
          "returnWin": 0,
          "returnPlace": 0
        }
      },
      {
        "runnerName": "SATIN SADIE",
        "runnerNumber": 4,
        "finishingPosition": 0,
        "trainerName": "ROSALYN HUME",
        "barrierNumber": 4,
        "riderDriverName": "",
        "claimAmount": 0,
        "fixedOdds": {
          "returnWin": 1.01,
          "returnWinOpen": 0,
          "returnPlace": 0,
          "bettingStatus": "LateScratched",
          "winDeduction": 0,
          "placeDeduction": 0,
          "propositionNumber": 160134,
          "scratchedTime": "2026-04-18T05:36:22+00:00"
        },
        "parimutuel": {
          "bettingStatus": "Scratched",
          "returnWin": 0,
          "returnPlace": 0
        }
      },
      {
        "runnerName": "....",
        "runnerNumber": 5,
        "finishingPosition": 0,
        "trainerName": null,
        "barrierNumber": 5,
        "riderDriverName": "",
        "claimAmount": 0,
        "fixedOdds": {},
        "parimutuel": {
          "bettingStatus": "Scratched",
          "returnWin": 0,
          "returnPlace": 0
        }
      },
      {
        "runnerName": "OUR GIRL SELKIE",
        "runnerNumber": 6,
        "finishingPosition": 4,
        "trainerName": "LINDA GORE",
        "barrierNumber": 6,
        "riderDriverName": "",
        "claimAmount": 0,
        "fixedOdds": {
          "returnWin": 2.5,
          "returnWinOpen": 1.95,
          "returnPlace": 1.35,
          "bettingStatus": "Loser",
          "winDeduction": 0,
          "placeDeduction": 0,
          "propositionNumber": 160136,
          "scratchedTime": null
        },
        "parimutuel": {
          "bettingStatus": "Normal",
          "returnWin": 2.8,
          "returnPlace": 0
        }
      },
      {
        "runnerName": "....",
        "runnerNumber": 7,
        "finishingPosition": 0,
        "trainerName": null,
        "barrierNumber": 7,
        "riderDriverName": "",
        "claimAmount": 0,
        "fixedOdds": {},
        "parimutuel": {
          "bettingStatus": "Scratched",
          "returnWin": 0,
          "returnPlace": 0
        }
      },
      {
        "runnerName": "COSTLY HABITS",
        "runnerNumber": 8,
        "finishingPosition": 2,
        "trainerName": "KYLE GOODWIN",
        "barrierNumber": 8,
        "riderDriverName": "",
        "claimAmount": 0,
        "fixedOdds": {
          "returnWin": 4.6,
          "returnWinOpen": 4.6,
          "returnPlace": 1.85,
          "bettingStatus": "Loser",
          "winDeduction": 0,
          "placeDeduction": 0,
          "propositionNumber": 160138,
          "scratchedTime": null
        },
        "parimutuel": {
          "bettingStatus": "Normal",
          "returnWin": 5,
          "returnPlace": 0
        }
      }
    ],
    "raceClassConditions": "Maiden",
    "hasFixedOdds": false,
    "hasParimutuel": true,
    "winBook": "http://internal-aviato-lb-212286492.ap-southeast-2.elb.amazonaws.com/historical-results/v4/TabcorpNSW/fixedodds/2026/4/19/book/GSMGMT_G12/propositions",
    "willHaveFixedOdds": true,
    "meeting": {
      "meetingDate": "2026-04-19",
      "location": "SA",
      "meetingName": "MOUNT GAMBIER",
      "raceType": "G",
      "venueMnemonic": "T",
      "sellCode": {
        "meetingCode": "T",
        "scheduledType": "G"
      }
    },
    "skyRacing": {
      "audio": "https://mediatabs.skyracing.com.au/Audio_Replay/2026/04/20260419MTGG01.mp3",
      "video": "https://mediatabs.skyracing.com.au/Race_Replay/2026/04/20260419MTGG01_V.mp4"
    },
    "pools": [
      {
        "poolStatusCode": "Paying",
        "wageringProduct": "Win",
        "poolTotal": 349.81,
        "jackpot": 0,
        "poolCloseTime": "2026-04-19T02:36:10+00:00",
        "legs": [
          {
            "legNumber": 1,
            "raceNumber": 1,
            "venueMnemonic": "T",
            "raceType": "G",
            "startTime": "2026-04-19T02:35:00+00:00"
          }
        ]
      },
      {
        "poolStatusCode": "Paying",
        "wageringProduct": "Place",
        "poolTotal": 6.95,
        "jackpot": 0,
        "poolCloseTime": "2026-04-18T20:12:40+00:00",
        "legs": [
          {
            "legNumber": 1,
            "raceNumber": 1,
            "venueMnemonic": "T",
            "raceType": "G",
            "startTime": "2026-04-19T02:35:00+00:00"
          }
        ]
      },
      {
        "poolStatusCode": "Paying",
        "wageringProduct": "Quinella",
        "poolTotal": 83.74,
        "jackpot": 0,
        "poolCloseTime": "2026-04-19T02:36:10+00:00",
        "legs": [
          {
            "legNumber": 1,
            "raceNumber": 1,
            "venueMnemonic": "T",
            "raceType": "G",
            "startTime": "2026-04-19T02:35:00+00:00"
          }
        ]
      },
      {
        "poolStatusCode": "Paying",
        "wageringProduct": "Exacta",
        "poolTotal": 89.92,
        "jackpot": 0,
        "poolCloseTime": "2026-04-19T02:36:10+00:00",
        "legs": [
          {
            "legNumber": 1,
            "raceNumber": 1,
            "venueMnemonic": "T",
            "raceType": "G",
            "startTime": "2026-04-19T02:35:00+00:00"
          }
        ]
      },
      {
        "poolStatusCode": "Paying",
        "wageringProduct": "Duet",
        "poolTotal": 0,
        "jackpot": 0,
        "poolCloseTime": "2026-04-18T20:12:40+00:00",
        "legs": [
          {
            "legNumber": 1,
            "raceNumber": 1,
            "venueMnemonic": "T",
            "raceType": "G",
            "startTime": "2026-04-19T02:35:00+00:00"
          }
        ]
      },
      {
        "poolStatusCode": "Paying",
        "wageringProduct": "Trifecta",
        "poolTotal": 175.76,
        "jackpot": 0,
        "poolCloseTime": "2026-04-19T02:36:10+00:00",
        "legs": [
          {
            "legNumber": 1,
            "raceNumber": 1,
            "venueMnemonic": "T",
            "raceType": "G",
            "startTime": "2026-04-19T02:35:00+00:00"
          }
        ]
      },
      {
        "poolStatusCode": "Paying",
        "wageringProduct": "FirstFour",
        "poolTotal": 103.51,
        "jackpot": 0,
        "poolCloseTime": "2026-04-19T02:36:10+00:00",
        "legs": [
          {
            "legNumber": 1,
            "raceNumber": 1,
            "venueMnemonic": "T",
            "raceType": "G",
            "startTime": "2026-04-19T02:35:00+00:00"
          }
        ]
      },
      {
        "poolStatusCode": "Paying",
        "wageringProduct": "RunningDouble",
        "poolTotal": 1,
        "jackpot": 0,
        "poolCloseTime": "2026-04-19T02:36:10+00:00",
        "legs": [
          {
            "legNumber": 1,
            "raceNumber": 1,
            "venueMnemonic": "T",
            "raceType": "G",
            "startTime": "2026-04-19T02:35:00+00:00"
          },
          {
            "legNumber": 2,
            "raceNumber": 2,
            "venueMnemonic": "T",
            "raceType": "G",
            "startTime": "2026-04-19T02:57:00+00:00"
          }
        ]
      },
      {
        "poolStatusCode": "Paying",
        "wageringProduct": "EarlyQuaddie",
        "poolTotal": 0.5,
        "jackpot": 0,
        "poolCloseTime": "2026-04-19T02:36:10+00:00",
        "legs": [
          {
            "legNumber": 1,
            "raceNumber": 1,
            "venueMnemonic": "T",
            "raceType": "G",
            "startTime": "2026-04-19T02:35:00+00:00"
          },
          {
            "legNumber": 2,
            "raceNumber": 2,
            "venueMnemonic": "T",
            "raceType": "G",
            "startTime": "2026-04-19T02:57:00+00:00"
          },
          {
            "legNumber": 3,
            "raceNumber": 3,
            "venueMnemonic": "T",
            "raceType": "G",
            "startTime": "2026-04-19T03:17:00+00:00"
          },
          {
            "legNumber": 4,
            "raceNumber": 4,
            "venueMnemonic": "T",
            "raceType": "G",
            "startTime": "2026-04-19T03:37:00+00:00"
          }
        ]
      }
    ],
    "dividends": [
      {
        "poolStatusCode": "Paying",
        "wageringProduct": "Win",
        "jackpotCarriedOver": 0,
        "poolCloseTime": "2026-04-19T02:36:10+00:00",
        "poolDividends": [
          {
            "selections": [
              1
            ],
            "amount": 5.8
          }
        ]
      },
      {
        "poolStatusCode": "Paying",
        "wageringProduct": "Place",
        "jackpotCarriedOver": 0,
        "poolCloseTime": "2026-04-18T20:12:40+00:00",
        "poolDividends": [
          {
            "selections": [
              "F"
            ],
            "amount": 0
          }
        ]
      },
      {
        "poolStatusCode": "Paying",
        "wageringProduct": "Quinella",
        "jackpotCarriedOver": 0,
        "poolCloseTime": "2026-04-19T02:36:10+00:00",
        "poolDividends": [
          {
            "selections": [
              1,
              8
            ],
            "amount": 23
          }
        ]
      },
      {
        "poolStatusCode": "Paying",
        "wageringProduct": "Exacta",
        "jackpotCarriedOver": 0,
        "poolCloseTime": "2026-04-19T02:36:10+00:00",
        "poolDividends": [
          {
            "selections": [
              1,
              8
            ],
            "amount": 39.8
          }
        ]
      },
      {
        "poolStatusCode": "Paying",
        "wageringProduct": "Duet",
        "jackpotCarriedOver": 0,
        "poolCloseTime": "2026-04-18T20:12:40+00:00",
        "poolDividends": [
          {
            "selections": [
              "F",
              "F"
            ],
            "amount": 0
          }
        ]
      },
      {
        "poolStatusCode": "Paying",
        "wageringProduct": "Trifecta",
        "jackpotCarriedOver": 0,
        "poolCloseTime": "2026-04-19T02:36:10+00:00",
        "poolDividends": [
          {
            "selections": [
              1,
              8,
              2
            ],
            "amount": 26.2
          }
        ]
      },
      {
        "poolStatusCode": "Paying",
        "wageringProduct": "FirstFour",
        "jackpotCarriedOver": 0,
        "poolCloseTime": "2026-04-19T02:36:10+00:00",
        "poolDividends": [
          {
            "selections": [
              1,
              8,
              2,
              6
            ],
            "amount": 37.3
          }
        ]
      }
    ]
  }
}